{
  "timestamp": 1760772676,
  "trends": [
    {
      "keyword": "구준엽 서희원 묘소",
      "score": 20,
      "maxscore": 20,
      "hashed": "b8c801357b510fb0",
      "delta": 0,
      "engine": "zum"
    },
    {
      "keyword": "오타니 3홈런",
      "score": 19,
      "maxscore": 19,
      "hashed": "e3e1cbe4fdfa8aed",
      "delta": 0,
      "engine": "zum"
    },
    {
      "keyword": "주우재 최홍만",
      "score": 18,
      "maxscore": 18,
      "hashed": "225dc45c0ecdd002",
      "delta": 0,
      "engine": "zum"
    },
    {
      "keyword": "전북 현대 우승",
      "score": 17,
      "maxscore": 17,
      "hashed": "0da1aa163de15274",
      "delta": 0,
      "engine": "zum"
    },
    {
      "keyword": "기성용 포항 재계약",
      "score": 16,
      "maxscore": 16,
      "hashed": "d282c4134c652541",
      "delta": 0,
      "engine": "zum"
    },
    {
      "keyword": "뉴비트 컴백 스케줄러",
      "score": 15,
      "maxscore": 15,
      "hashed": "828681b53fd75e39",
      "delta": 0,
      "engine": "zum"
    },
    {
      "keyword": "울진공항 경비행기 불시착",
      "score": 14,
      "maxscore": 14,
      "hashed": "f138d164e5e38673",
      "delta": 0,
      "engine": "zum"
    },
    {
      "keyword": "캄보디아 구금 한국인",
      "score": 13,
      "maxscore": 13,
      "hashed": "bca8b4f67e62764d",
      "delta": 0,
      "engine": "zum"
    },
    {
      "keyword": "포스테코글루 경질 위기",
      "score": 12,
      "maxscore": 12,
      "hashed": "a60fcbc440ea32d2",
      "delta": 0,
      "engine": "zum"
    },
    {
      "keyword": "박진만 감독",
      "score": 11,
      "maxscore": 11,
      "hashed": "c6249d35c0974852",
      "delta": 0,
      "engine": "zum"
    }
  ],
  "updated": "2025-10-18T07:31:17.932Z"
}