{
  "timestamp": 1760583020,
  "trends": [
    {
      "keyword": "최태원 노소영 파기환송",
      "score": 20,
      "maxscore": 20,
      "hashed": "7d1c1bf5271392b8",
      "delta": 999,
      "engine": "zum"
    },
    {
      "keyword": "신랑수업 장우혁 오채이",
      "score": 19,
      "maxscore": 19,
      "hashed": "d6cc7b463ca3caed",
      "delta": -1,
      "engine": "zum"
    },
    {
      "keyword": "백해룡 불법단체 비판",
      "score": 18,
      "maxscore": 18,
      "hashed": "a91dc172a508ff77",
      "delta": 1,
      "engine": "zum"
    },
    {
      "keyword": "장호진 안보실장 이종섭 도피 의혹",
      "score": 17,
      "maxscore": 17,
      "hashed": "cf7a132d3a03777c",
      "delta": 999,
      "engine": "zum"
    },
    {
      "keyword": "양평고속도로 국토부 압수수색",
      "score": 16,
      "maxscore": 16,
      "hashed": "0886e75bad5fb285",
      "delta": -2,
      "engine": "zum"
    },
    {
      "keyword": "손연재 결혼 스토리",
      "score": 15,
      "maxscore": 15,
      "hashed": "3e9a5b30b0c0c3c4",
      "delta": 999,
      "engine": "zum"
    },
    {
      "keyword": "한화 폰세 가라비토",
      "score": 14,
      "maxscore": 14,
      "hashed": "1a204e7db7c93e35",
      "delta": 999,
      "engine": "zum"
    },
    {
      "keyword": "진태현 김우빈 미담",
      "score": 13,
      "maxscore": 13,
      "hashed": "177341d1a6ed93f2",
      "delta": 999,
      "engine": "zum"
    },
    {
      "keyword": "대통령 K-바이오 규제",
      "score": 12,
      "maxscore": 12,
      "hashed": "884d5685c7417260",
      "delta": 999,
      "engine": "zum"
    },
    {
      "keyword": "조현준 효성 횡령 혐의",
      "score": 11,
      "maxscore": 11,
      "hashed": "f4670232ef807b0d",
      "delta": 999,
      "engine": "zum"
    }
  ],
  "created_at": "2025-10-16T02:50:23.624Z"
}